pymoood/Emotion_Analysis_English.py
pymoood/__init__.py
pymoood/badword.py
pymoood/badword_lsit.txt
pymoood/chatbot.py
pymoood/emoji_model
pymoood/emotion_for_playlist_model.sav
pymoood/emotion_label_encoder.pkl
pymoood/emotion_mlp_model.sav
pymoood/emotion_vectorizer.pkl
pymoood/playlist.py
pymoood/sentence_emotion.py
pymoood/text_vectorizer
pymoood/vectorizer_for_playlist.sav
pymoood-0.0.2.dist-info/METADATA
pymoood-0.0.2.dist-info/WHEEL
pymoood-0.0.2.dist-info/licenses/LICENSE
pymoood-0.0.2.dist-info/RECORD
