Metadata-Version: 2.3
Name: pymoood
Version: 0.0.2
Summary: This is a package that changes emotions into emoticons.
Project-URL: Homepage, https://github.com/JOGUNHEE14/oss_project
Project-URL: Issues, https://github.com/JOGUNHEE14/oss_project/issues
Author-email: oss_project <arijo2123@hanyang.ac.kr>
Classifier: License :: OSI Approved :: MIT License
Classifier: Operating System :: OS Independent
Classifier: Programming Language :: Python :: 3
Requires-Python: >=3.8
